zpack-0.1.17.dist-info/METADATA
zpack-0.1.17.dist-info/WHEEL
zpack-0.1.17.dist-info/entry_points.txt
zpack-0.1.17.dist-info/licenses/LICENSE
zpack/__init__.py
zpack/zpack.cp311-win_arm64.pyd
zpack-0.1.17.dist-info/RECORD
