Metadata-Version: 2.4
Name: zpack
Version: 0.1.17
Classifier: Programming Language :: Rust
Classifier: Programming Language :: Python :: Implementation :: CPython
Classifier: Programming Language :: Python :: Implementation :: PyPy
Requires-Dist: maturin>=1.9.4
License-File: LICENSE
Home-Page: https://github.com/Pencilcaseman/zpack
Requires-Python: >=3.8
